wispra/__init__.py
wispra/pl.py
wispra/tl.py
wispra-0.9.2.dist-info/licenses/LICENSE.txt
wispra-0.9.2.dist-info/METADATA
wispra-0.9.2.dist-info/WHEEL
wispra-0.9.2.dist-info/top_level.txt
wispra-0.9.2.dist-info/RECORD
