Metadata-Version: 2.4
Name: wispra
Version: 0.9.2
Summary: A package designed to analysis cell-to-cell interaction in single-cell resolution.
Author-email: Wang Zilu <1923524070@qq.com>
License-Expression: MIT
Project-URL: Homepage, https://github.com/wangz1lu/wispra
Project-URL: Bug Tracker, https://github.com/wangz1lu/wispra/issues
Classifier: Programming Language :: Python :: 3
Classifier: Operating System :: OS Independent
Requires-Python: >=3.7
License-File: LICENSE.txt
Requires-Dist: numpy
Requires-Dist: pandas
Requires-Dist: matplotlib
Requires-Dist: seaborn
Requires-Dist: tqdm
Requires-Dist: scipy
Requires-Dist: anndata
Requires-Dist: scikit-learn
Requires-Dist: collections
Requires-Dist: torch
Requires-Dist: statsmodels
Dynamic: license-file
